parsomics_cli/__init__.py
parsomics_cli/backend/analysis/types.py
parsomics_cli/backend/analysis/utils.py
parsomics_cli/backend/config/exc.py
parsomics_cli/backend/config/types.py
parsomics_cli/backend/config/utils.py
parsomics_cli/backend/database/exc.py
parsomics_cli/backend/database/types.py
parsomics_cli/backend/database/utils.py
parsomics_cli/backend/plugins/exc.py
parsomics_cli/backend/plugins/utils.py
parsomics_cli/frontend/analysis.py
parsomics_cli/frontend/app.py
parsomics_cli/frontend/config.py
parsomics_cli/frontend/database.py
parsomics_cli/frontend/helpers.py
parsomics_cli/frontend/password.py
parsomics_cli/frontend/plugins.py
parsomics_cli/frontend/setup.py
parsomics_cli/main.py
parsomics_cli/parsomics-registry/.git
parsomics_cli/parsomics-registry/README.md
parsomics_cli/parsomics-registry/hash.py
parsomics_cli/parsomics-registry/plugins.json
parsomics_cli/parsomics-registry/plugins.json.hash
parsomics_cli/parsomics-registry/public.asc
parsomics_cli-2.3.1.dist-info/METADATA
parsomics_cli-2.3.1.dist-info/WHEEL
parsomics_cli-2.3.1.dist-info/entry_points.txt
parsomics_cli-2.3.1.dist-info/RECORD
